searchsplunk/__init__.py
searchsplunk/exceptions.py
searchsplunk/searchsplunk.py
searchsplunk/version.py
searchsplunk-0.2.1.dist-info/DESCRIPTION.rst
searchsplunk-0.2.1.dist-info/METADATA
searchsplunk-0.2.1.dist-info/RECORD
searchsplunk-0.2.1.dist-info/WHEEL
searchsplunk-0.2.1.dist-info/metadata.json
searchsplunk-0.2.1.dist-info/top_level.txt
