Metadata-Version: 2.0
Name: searchsplunk
Version: 0.2.1
Summary: Splunk search client
Home-page: https://github.com/ryancurrah/searchsplunk
Author: Ryan Currah
Author-email: ryan@currah.ca
License: GPLv2
Keywords: splunk,search
Platform: UNKNOWN
Classifier: Programming Language :: Python :: 2
Classifier: Programming Language :: Python :: 2.7
Classifier: Programming Language :: Python :: 3
Classifier: Programming Language :: Python :: 3.3
Classifier: Programming Language :: Python :: 3.4
Classifier: Programming Language :: Python :: 3.5
Requires-Dist: requests (>=2.7.0)
